Metadata-Version: 2.1
Name: django-allauth-microsoft
Version: 1.0.1
Summary: Microsoft OAuth2 provider for django-allauth
Home-page: https://github.com/schaenzer/django-allauth-microsoft
Author: Muhammed Mehmood
Author-email: ifreezeu2@gmail.com
License: UNKNOWN
Platform: UNKNOWN
Classifier: Programming Language :: Python
Classifier: Operating System :: OS Independent
Classifier: Framework :: Django
License-File: LICENSE
